randovania_scm_version_schema/__init__.py
randovania_scm_version_schema-0.3.2.dist-info/LICENSE
randovania_scm_version_schema-0.3.2.dist-info/METADATA
randovania_scm_version_schema-0.3.2.dist-info/WHEEL
randovania_scm_version_schema-0.3.2.dist-info/top_level.txt
randovania_scm_version_schema-0.3.2.dist-info/RECORD
