Metadata-Version: 2.1
Name: randovania-scm-version-schema
Version: 0.3.2
Summary: setuptools-scm version_schema hook for randovania
Author: Henrique Gemignani Passos Lima
License: Apache License
Project-URL: Homepage, https://github.com/randovania/randovania-scm-version-schema
Classifier: Development Status :: 5 - Production/Stable
Classifier: Environment :: Console
Classifier: Intended Audience :: Developers
Classifier: License :: OSI Approved :: Apache Software License
Classifier: Programming Language :: Python :: 3 :: Only
Classifier: Programming Language :: Python :: 3.9
Classifier: Programming Language :: Python :: 3.10
Classifier: Programming Language :: Python :: 3.11
Classifier: Programming Language :: Python :: 3.12
Classifier: Programming Language :: Python :: 3.13
Requires-Python: >=3.9
License-File: LICENSE
Requires-Dist: setuptools >=64
Requires-Dist: setuptools-scm >=8
Requires-Dist: dulwich
Provides-Extra: test
Requires-Dist: pytest ; extra == 'test'
Requires-Dist: pytest-cov ; extra == 'test'
Requires-Dist: pytest-mock ; extra == 'test'
